{
    "created": "2019-06-11T14:18:18.874+00:00",
    "deprecated": false,
    "deprecationDate": null,
    "deprecationOfflineDate": null,
    "deprecationStatement": null,
    "description": "The cBioPortal for Cancer Genomics provides visualization, analysis and download of large-scale cancer genomics data sets.",
    "id": 1881,
    "infoOnPostmortemAccess": null,
    "mirId": "MIR:00000679",
    "modified": "2019-06-11T14:18:18.874+00:00",
    "name": "The cBioPortal for Cancer Genomics",
    "namespaceEmbeddedInLui": false,
    "pattern": "^[a-z0-9\\_]+$",
    "prefix": "cbioportal",
    "renderDeprecatedLanding": false,
    "resources": [
        {
            "authHelpDescription": null,
            "authHelpUrl": null,
            "deprecated": false,
            "deprecationDate": null,
            "deprecationOfflineDate": null,
            "deprecationStatement": null,
            "description": "The cBioPortal for Cancer Genomics",
            "id": 1883,
            "institution": {
                "description": "The people of Memorial Sloan Kettering Cancer Center (MSK) are united by a singular mission: ending cancer for life. Our specialized care teams provide personalized, compassionate, expert care to patients of all ages. Informed by basic research done at our Sloan Kettering Institute, scientists across MSK collaborate to conduct innovative translational and clinical research that is driving a revolution in our understanding of cancer as a disease and improving the ability to prevent, diagnose, and treat it. MSK is dedicated to training the next generation of scientists and clinicians, who go on to pursue our mission at MSK and around the globe. One of the world’s most respected comprehensive centers devoted exclusively to cancer, we have been recognized as one of the top two cancer hospitals in the country by U.S. News & World Report for more than 30 years. ",
                "homeUrl": "https://www.mskcc.org/",
                "id": 1882,
                "location": {
                    "countryCode": "US",
                    "countryName": "United States"
                },
                "name": "Memorial Sloan Kettering Cancer Center",
                "rorId": "https://ror.org/02yrq0923"
            },
            "location": {
                "countryCode": "US",
                "countryName": "United States"
            },
            "mirId": "MIR:00100909",
            "name": "The cBioPortal for Cancer Genomics",
            "official": false,
            "protectedUrls": false,
            "providerCode": "CURATOR_REVIEW",
            "renderDeprecatedLanding": false,
            "renderProtectedLanding": false,
            "resourceHomeUrl": "http://www.cbioportal.org",
            "sampleId": "laml_tcga_pub",
            "urlPattern": "http://www.cbioportal.org/study?id={$id}#summary"
        }
    ],
    "sampleId": "laml_tcga_pub",
    "successor": null
}